{
  "type": "doc",
  "content": [
    {
      "type": "imageExtension",
      "attrs": {
        "alt": "Image from URL",
        "src": "https://vignan.ac.in/newvignan/assets/images/Logo%20with%20Deemed.svg",
        "align": "center",
        "title": null,
        "width": null,
        "height": null,
        "rotate": 0
      }
    },
    {
      "type": "heading",
      "attrs": {
        "level": 1,
        "textAlign": null
      },
      "content": [
        {
          "text": "The Impact of Remote Work on Employee Productivity and Well-Being",
          "type": "text",
          "marks": [
            {
              "type": "textStyle",
              "attrs": {
                "fontFamily": "Arial"
              }
            }
          ]
        }
      ]
    },
    {
      "type": "heading",
      "attrs": {
        "level": 1,
        "textAlign": null
      },
      "content": [
        {
          "text": "Student Name",
          "type": "text",
          "marks": [
            {
              "type": "textStyle",
              "attrs": {
                "fontFamily": "Arial"
              }
            },
            {
              "type": "bold"
            }
          ]
        }
      ]
    },
    {
      "type": "heading",
      "attrs": {
        "level": 1,
        "textAlign": null
      },
      "content": [
        {
          "type": "hardBreak",
          "marks": [
            {
              "type": "textStyle",
              "attrs": {
                "fontFamily": "Arial"
              }
            }
          ]
        },
        {
          "text": "Department / Program",
          "type": "text",
          "marks": [
            {
              "type": "textStyle",
              "attrs": {
                "fontFamily": "Arial"
              }
            }
          ]
        },
        {
          "type": "hardBreak",
          "marks": [
            {
              "type": "textStyle",
              "attrs": {
                "fontFamily": "Arial"
              }
            }
          ]
        },
        {
          "text": "Institution Name",
          "type": "text",
          "marks": [
            {
              "type": "textStyle",
              "attrs": {
                "fontFamily": "Arial"
              }
            }
          ]
        },
        {
          "type": "hardBreak",
          "marks": [
            {
              "type": "textStyle",
              "attrs": {
                "fontFamily": "Arial"
              }
            }
          ]
        },
        {
          "text": "Date",
          "type": "text",
          "marks": [
            {
              "type": "textStyle",
              "attrs": {
                "fontFamily": "Arial"
              }
            }
          ]
        }
      ]
    },
    {
      "type": "horizontalRule"
    },
    {
      "type": "paragraph",
      "attrs": {
        "textAlign": null
      },
      "content": [
        {
          "text": "Abstract",
          "type": "text",
          "marks": [
            {
              "type": "textStyle",
              "attrs": {
                "fontFamily": "Arial"
              }
            }
          ]
        }
      ]
    },
    {
      "type": "orderedList",
      "attrs": {
        "type": null,
        "start": 1
      },
      "content": [
        {
          "type": "listItem",
          "content": [
            {
              "type": "paragraph",
              "attrs": {
                "textAlign": "justify"
              },
              "content": [
                {
                  "text": "The rapid adoption of remote work has transformed traditional organizational structures and work practices across multiple industries",
                  "type": "text",
                  "marks": [
                    {
                      "type": "textStyle",
                      "attrs": {
                        "fontFamily": "Arial"
                      }
                    },
                    {
                      "type": "bold"
                    }
                  ]
                },
                {
                  "text": ". While remote work offers flexibility and potential p",
                  "type": "text",
                  "marks": [
                    {
                      "type": "textStyle",
                      "attrs": {
                        "fontFamily": "Arial"
                      }
                    }
                  ]
                },
                {
                  "text": "roductivity benefits, it also introduces challenges related to communication, collaboration, and employee well-being. This paper examines the effects of remote work on employee productivity and psychological health, focusing on both positive outcomes and emerging ",
                  "type": "text",
                  "marks": [
                    {
                      "type": "textStyle",
                      "attrs": {
                        "fontFamily": "Arial"
                      }
                    },
                    {
                      "type": "italic"
                    }
                  ]
                },
                {
                  "text": "risks. The analysis highlights the need for balanced organizational strategies that support performance while addressing social and mental health concerns.(Fei Zhou, Ting Yu, Ronghui Du, Guohui Fan, Ying Liu, Zhibo Liu, Jie Xiang, Yeming Wang, Bin Song, Xiaoying Gu, Lulu Guan, Yuan Wei, Hui Li, Xudong Wu, Jiuyang Xu, Shengjin Tu, Yi Zhang, Hua Chen, Bin Cao 2020)(Chaolin Huang et al. 2020)[1]",
                  "type": "text",
                  "marks": [
                    {
                      "type": "textStyle",
                      "attrs": {
                        "fontFamily": "Arial"
                      }
                    }
                  ]
                }
              ]
            }
          ]
        }
      ]
    },
    {
      "type": "horizontalRule"
    },
    {
      "type": "heading",
      "attrs": {
        "level": 2,
        "textAlign": null
      },
      "content": [
        {
          "text": "Introduction",
          "type": "text"
        }
      ]
    },
    {
      "type": "paragraph",
      "attrs": {
        "textAlign": null
      },
      "content": [
        {
          "text": "Remote work has shifted from a niche employment arrangement to a mainstream work model.[1] Advances in digital communication technologies and changing workforce expectations have enabled organizations to operate beyond physical office spaces.(Chaolin Huang et al.)",
          "type": "text"
        }
      ]
    },
    {
      "type": "paragraph",
      "attrs": {
        "textAlign": null
      }
    },
    {
      "type": "paragraph",
      "attrs": {
        "textAlign": null
      },
      "content": [
        {
          "text": ". This transition accelerated significantly during global disruptions, forcing companies to adopt remote work policies at scale. As organizations continue to evaluate long-term remote and hybrid models, understanding their impact on employee productivity and well-being has become increasingly important.(Chaolin Huang, Ye-ming Wang, Xing-wang Li, L. Ren, Jianping Zhao, Y. Hu, Li Zhang, Guohui Fan, Jiuyang Xu, Xiaoying Gu, Zhenshun Cheng, Ting Yu, Jia’an Xia, Yuan Wei, Wenjuan Wu, Xuelei Xie, Wen Yin, Hui Li, Min Liu, Yan Xiao, Hong Gao, Li Guo, Jungang Xie, Guangfa Wang, R. Jiang, Zhancheng Gao, Q. Jin, Jianwei Wang, B. Cao, 2020)",
          "type": "text"
        }
      ]
    },
    {
      "type": "paragraph",
      "attrs": {
        "textAlign": null
      },
      "content": [
        {
          "text": "Productivity has traditionally been associated with structured office environments, direct supervision, and standardized workflows. Remote work challenges these assumptions by emphasizing autonomy and outcome-based performance. At the same time, employees face new stressors such as social isolation, blurred work-life boundaries, and increased reliance on digital communication.(Chaolin Huang et al. 2020)(Chaolin Huang et al.)",
          "type": "text"
        }
      ]
    },
    {
      "type": "horizontalRule"
    },
    {
      "type": "heading",
      "attrs": {
        "level": 2,
        "textAlign": null
      },
      "content": [
        {
          "text": "Methodology",
          "type": "text"
        }
      ]
    },
    {
      "type": "paragraph",
      "attrs": {
        "textAlign": null
      },
      "content": [
        {
          "text": "This study adopts a qualitative analytical approach based on synthesized observations from organizational reports, employee surveys, and workplace behavior analyses. Rather than relying on experimental data, the paper focuses on identifying common patterns and themes observed in remote work environments. The methodology emphasizes comparative evaluation of employee experiences before and after transitioning to remote work.",
          "type": "text"
        },
        {
          "type": "hardBreak"
        }
      ]
    },
    {
      "type": "paragraph",
      "attrs": {
        "textAlign": null
      },
      "content": [
        {
          "text": "Key variables examined include perceived productivity, task completion efficiency, work-life balance, communication effectiveness, and psychological well-being. These variables are analyzed to identify recurring trends and organizational implications.(Chaolin Huang, Ye-ming Wang, Xing-wang Li, L. Ren, Jianping Zhao, Y. Hu, Li Zhang, Guohui Fan, Jiuyang Xu, Xiaoying Gu, Zhenshun Cheng, Ting Yu, Jia’an Xia, Yuan Wei, Wenjuan Wu, Xuelei Xie, Wen Yin, Hui Li, Min Liu, Yan Xiao, Hong Gao, Li Guo, Jungang Xie, Guangfa Wang, R. Jiang, Zhancheng Gao, Q. Jin, Jianwei Wang, B. Cao, 2020)(Chaolin Huang, Ye-ming Wang, Xing-wang Li, L. Ren, Jianping Zhao, Y. Hu, Li Zhang, Guohui Fan, Jiuyang Xu, Xiaoying Gu, Zhenshun Cheng, Ting Yu, Jia’an Xia, Yuan Wei, Wenjuan Wu, Xuelei Xie, Wen Yin, Hui Li, Min Liu, Yan Xiao, Hong Gao, Li Guo, Jungang Xie, Guangfa Wang, R. Jiang, Zhancheng Gao, Q. Jin, Jianwei Wang, B. Cao 2020)",
          "type": "text"
        }
      ]
    },
    {
      "type": "horizontalRule"
    },
    {
      "type": "heading",
      "attrs": {
        "level": 2,
        "textAlign": null
      },
      "content": [
        {
          "text": "Results",
          "type": "text"
        }
      ]
    },
    {
      "type": "paragraph",
      "attrs": {
        "textAlign": null
      },
      "content": [
        {
          "text": "The analysis indicates that remote work can enhance productivity for employees who benefit from flexible schedules and reduced commuting time. Many individuals report improved concentration and greater control over their work environment. Productivity gains are most evident in roles that require independent task execution and minimal synchronous collaboration.",
          "type": "text"
        }
      ]
    },
    {
      "type": "paragraph",
      "attrs": {
        "textAlign": null
      },
      "content": [
        {
          "text": "However, the results also reveal challenges. Employees frequently experience difficulties in maintaining clear work-life boundaries, leading to extended working hours. Communication delays and reduced informal interaction contribute to feelings of disconnection from colleagues. Over time, these factors may negatively affect morale and job satisfaction.",
          "type": "text"
        }
      ]
    },
    {
      "type": "horizontalRule"
    },
    {
      "type": "heading",
      "attrs": {
        "level": 2,
        "textAlign": null
      },
      "content": [
        {
          "text": "Discussion",
          "type": "text"
        }
      ]
    },
    {
      "type": "paragraph",
      "attrs": {
        "textAlign": null
      },
      "content": [
        {
          "text": "The findings suggest that remote work productivity is highly context-dependent. Individual work styles, job roles, and organizational support mechanisms play a significant role in determining outcomes. Employees with strong self-management skills tend to thrive, while others struggle without structured oversight.",
          "type": "text"
        }
      ]
    },
    {
      "type": "paragraph",
      "attrs": {
        "textAlign": null
      },
      "content": [
        {
          "text": "Well-being concerns emerge primarily from social isolation and constant digital engagement. Organizations that fail to address these issues risk long-term declines in employee engagement. Implementing structured communication practices, encouraging regular breaks, and fostering virtual social interaction can mitigate negative effects.",
          "type": "text"
        }
      ]
    },
    {
      "type": "horizontalRule"
    },
    {
      "type": "heading",
      "attrs": {
        "level": 2,
        "textAlign": null
      },
      "content": [
        {
          "text": "Conclusion",
          "type": "text"
        }
      ]
    },
    {
      "type": "paragraph",
      "attrs": {
        "textAlign": null
      },
      "content": [
        {
          "text": "Remote work represents a fundamental shift in how organizations operate and how employees engage with their work. While it offers clear productivity advantages in certain contexts, it also introduces challenges that can impact employee well-being. Organizations must adopt intentional strategies to balance flexibility with support, ensuring sustainable performance and healthy work environments. Future research should explore long-term outcomes of hybrid work models and their implications for organizational culture.",
          "type": "text"
        }
      ]
    },
    {
      "type": "heading",
      "attrs": {
        "level": 2,
        "textAlign": null
      },
      "content": [
        {
          "text": "References",
          "type": "text"
        }
      ]
    },
    {
      "type": "paragraph",
      "attrs": {
        "textAlign": null
      },
      "content": [
        {
          "text": "Fei Zhou, Ting Yu, Ronghui Du, Guohui Fan, Ying Liu, Zhibo Liu, Jie Xiang, Yeming Wang, Bin Song, Xiaoying Gu, Lulu Guan, Yuan Wei, Hui Li, Xudong Wu, Jiuyang Xu, Shengjin Tu, Yi Zhang, Hua Chen, Bin Cao. 2020. \"Clinical course and risk factors for mortality of adult inpatients with COVID-19 in Wuhan, China: a retrospective cohort study.\" .",
          "type": "text"
        }
      ]
    },
    {
      "type": "paragraph",
      "attrs": {
        "textAlign": null
      },
      "content": [
        {
          "text": "[1] Fei Zhou, Ting Yu, Ronghui Du, Guohui Fan, Ying Liu, Zhibo Liu, Jie Xiang, Yeming Wang, Bin Song, Xiaoying Gu, Lulu Guan, Yuan Wei, Hui Li, Xudong Wu, Jiuyang Xu, Shengjin Tu, Yi Zhang, Hua Chen, Bin Cao, \"Clinical course and risk factors for mortality of adult inpatients with COVID-19 in Wuhan, China: a retrospective cohort study,\" 2020.",
          "type": "text"
        }
      ]
    },
    {
      "type": "paragraph",
      "attrs": {
        "textAlign": null
      },
      "content": [
        {
          "text": "Chaolin Huang, Ye-ming Wang, Xing-wang Li, L. Ren, Jianping Zhao, Y. Hu, Li Zhang, Guohui Fan, Jiuyang Xu, Xiaoying Gu, Zhenshun Cheng, Ting Yu, Jia’an Xia, Yuan Wei, Wenjuan Wu, Xuelei Xie, Wen Yin, Hui Li, Min Liu, Yan Xiao, Hong Gao, Li Guo, Jungang Xie, Guangfa Wang, R. Jiang, Zhancheng Gao, Q. Jin, Jianwei Wang, B. Cao (2020). [Asymptomatic infection of COVID-19 and its challenge to epidemic prevention and control].. .",
          "type": "text"
        }
      ]
    },
    {
      "type": "paragraph",
      "attrs": {
        "textAlign": null
      },
      "content": [
        {
          "text": "Chaolin Huang, Ye-ming Wang, Xing-wang Li, L. Ren, Jianping Zhao, Y. Hu, Li Zhang, Guohui Fan, Jiuyang Xu, Xiaoying Gu, Zhenshun Cheng, Ting Yu, Jia’an Xia, Yuan Wei, Wenjuan Wu, Xuelei Xie, Wen Yin, Hui Li, Min Liu, Yan Xiao, Hong Gao, Li Guo, Jungang Xie, Guangfa Wang, R. Jiang, Zhancheng Gao, Q. Jin, Jianwei Wang, B. Cao. 2020. \"[Asymptomatic infection of COVID-19 and its challenge to epidemic prevention and control]..\" .",
          "type": "text"
        }
      ]
    },
    {
      "type": "paragraph",
      "attrs": {
        "textAlign": null
      },
      "content": [
        {
          "text": "Chaolin Huang, Ye-ming Wang, Xing-wang Li, L. Ren, Jianping Zhao, Y. Hu, Li Zhang, et al.. 2020. \"[Asymptomatic infection of COVID-19 and its challenge to epidemic prevention and control]..\" .",
          "type": "text"
        }
      ]
    },
    {
      "type": "paragraph",
      "attrs": {
        "textAlign": null
      },
      "content": [
        {
          "text": "Chaolin Huang et al.. \"[Asymptomatic infection of COVID-19 and its challenge to epidemic prevention and control]..\"  2020.",
          "type": "text"
        }
      ]
    },
    {
      "type": "paragraph",
      "attrs": {
        "textAlign": null
      },
      "content": [
        {
          "text": "[1] Fei Zhou, Ting Yu, Ronghui Du, Guohui Fan, Ying Liu, Zhibo Liu, Jie Xiang, Yeming Wang, Bin Song, Xiaoying Gu, Lulu Guan, Yuan Wei, Hui Li, Xudong Wu, Jiuyang Xu, Shengjin Tu, Yi Zhang, Hua Chen, and Bin Cao, \"Clinical course and risk factors for mortality of adult inpatients with COVID-19 in Wuhan, China: a retrospective cohort study,\" 2020.",
          "type": "text"
        }
      ]
    },
    {
      "type": "paragraph",
      "attrs": {
        "textAlign": null
      },
      "content": [
        {
          "text": "https://vignan.ac.in/newvignan/assets/images/Logo%20with%20Deemed.svg",
          "type": "text",
          "marks": [
            {
              "type": "link",
              "attrs": {
                "rel": "noopener noreferrer",
                "href": "https://vignan.ac.in/newvignan/assets/images/Logo%20with%20Deemed.svg",
                "class": null,
                "target": "_blank"
              }
            }
          ]
        }
      ]
    },
    {
      "type": "paragraph",
      "attrs": {
        "textAlign": null
      }
    }
  ]
}